synforge/__init__.py
synforge/agent.py
synforge/llm_providers.py
synforge/messages.py
synforge/multi_agent.py
synforge/prompts.py
synforge/tasks.py
synforge/utils.py
synforge/output/output.json
synforge-0.1.0.dist-info/METADATA
synforge-0.1.0.dist-info/WHEEL
synforge-0.1.0.dist-info/licenses/LICENSE
synforge-0.1.0.dist-info/RECORD
